gpts_builder/__init__.py
gpts_builder/prompt_base_builder.py
gpts_builder/prompt_template.py
gpts_builder/builder/__init__.py
gpts_builder/builder/llm/__init__.py
gpts_builder/builder/llm/base_builder.py
gpts_builder/builder/llm/llm_base_builder.py
gpts_builder/builder/llm/llm_builder.py
gpts_builder/builder/plugin/__init__.py
gpts_builder/builder/plugin/base_builder.py
gpts_builder/builder/plugin/kb_builder.py
gpts_builder/builder/prompt/__init__.py
gpts_builder/builder/prompt/base_builder.py
gpts_builder/builder/prompt/builder.py
gpts_builder/builder/prompt/builder_async.py
gpts_builder/builder/prompt/template.py
gpts_builder/builder/rag/__init__.py
gpts_builder/builder/rag/dataset_builder.py
gpts_builder/builder_async/__init__.py
gpts_builder/builder_async/llm/__init__.py
gpts_builder/builder_async/llm/llm_async_builder.py
gpts_builder/builder_async/llm/llm_base_builder.py
gpts_builder/builder_async/plugin/__init__.py
gpts_builder/builder_async/prompt/__init__.py
gpts_builder/builder_async/prompt/builder_async.py
gpts_builder/builder_async/rag/__init__.py
gpts_builder/builder_async/rag/dataset_builder_async.py
gpts_builder/config/__init__.py
gpts_builder/config/config_manager.py
gpts_builder/config/config_template.py
gpts_builder/session_manager/__init__ copy.py
gpts_builder/session_manager/__init__.py
gpts_builder/session_manager/base_session.py
gpts_builder/session_manager/chatgpt_session.py
gpts_builder/session_manager/session_manager.py
gpts_builder/session_manager/session_manager_async.py
gpts_builder/session_manager/storage/__init__.py
gpts_builder/session_manager/storage/global_storage.py
gpts_builder/session_manager/storage/redis_storage.py
gpts_builder/session_manager/storage/redis_storage_async.py
gpts_builder/util/__init__.py
gpts_builder/util/context.py
gpts_builder/util/datetime_utils.py
gpts_builder/util/file_utils.py
gpts_builder/util/function_timer.py
gpts_builder/util/http_client.py
gpts_builder/util/id_generator.py
gpts_builder/util/logger.py
gpts_builder-0.1.20.dist-info/LICENSE
gpts_builder-0.1.20.dist-info/METADATA
gpts_builder-0.1.20.dist-info/WHEEL
gpts_builder-0.1.20.dist-info/top_level.txt
gpts_builder-0.1.20.dist-info/RECORD
