Metadata-Version: 2.1
Name: gpts_builder
Version: 0.1.20
Summary: A Python library for quickly building applications with large language models.
Home-page: https://github.com/yancyuu/gpts_builder.git
Author: yancyyu
Author-email: yancyyu.ok@gmail.com
License: MIT
Keywords: GPT,large language models,AI,application builder
Classifier: Programming Language :: Python :: 3
Classifier: License :: OSI Approved :: MIT License
Classifier: Operating System :: OS Independent
Requires-Python: >=3.6
License-File: LICENSE
Requires-Dist: aioredis <3,>=1.3
Requires-Dist: anyio ==4.3.0
Requires-Dist: async-timeout ==4.0.3
Requires-Dist: backoff ==2.2.1
Requires-Dist: certifi ==2024.2.2
Requires-Dist: charset-normalizer ==3.3.2
Requires-Dist: httpx ==0.27.0
Requires-Dist: redis ==5.0.4
Requires-Dist: regex ==2024.4.28
Requires-Dist: requests ==2.31.0
Requires-Dist: sniffio ==1.3.1
Requires-Dist: tiktoken ==0.6.0
Requires-Dist: typing-extensions ==4.11.0
Requires-Dist: urllib3 ==2.2.1
